[{"Name":"__ddg8_","Value":"r0fLsy67GWK53VML","Quoted":false,"Path":"","Domain":"","Expires":"0001-01-01T00:00:00Z","RawExpires":"","MaxAge":0,"Secure":false,"HttpOnly":false,"SameSite":0,"Partitioned":false,"Raw":"","Unparsed":null},{"Name":"__ddg10_","Value":"1741988659","Quoted":false,"Path":"","Domain":"","Expires":"0001-01-01T00:00:00Z","RawExpires":"","MaxAge":0,"Secure":false,"HttpOnly":false,"SameSite":0,"Partitioned":false,"Raw":"","Unparsed":null},{"Name":"__ddg9_","Value":"185.189.25.68","Quoted":false,"Path":"","Domain":"","Expires":"0001-01-01T00:00:00Z","RawExpires":"","MaxAge":0,"Secure":false,"HttpOnly":false,"SameSite":0,"Partitioned":false,"Raw":"","Unparsed":null},{"Name":"__ddgid_","Value":"Ile9i6szyUMEpXVM","Quoted":false,"Path":"","Domain":"","Expires":"0001-01-01T00:00:00Z","RawExpires":"","MaxAge":0,"Secure":false,"HttpOnly":false,"SameSite":0,"Partitioned":false,"Raw":"","Unparsed":null},{"Name":"__ddgmark_","Value":"pB0Kx2RNsdrLWOJe","Quoted":false,"Path":"","Domain":"","Expires":"0001-01-01T00:00:00Z","RawExpires":"","MaxAge":0,"Secure":false,"HttpOnly":false,"SameSite":0,"Partitioned":false,"Raw":"","Unparsed":null},{"Name":"__ddg5_","Value":"zocYhKNTdXXIurSX","Quoted":false,"Path":"","Domain":"","Expires":"0001-01-01T00:00:00Z","RawExpires":"","MaxAge":0,"Secure":false,"HttpOnly":false,"SameSite":0,"Partitioned":false,"Raw":"","Unparsed":null},{"Name":"__ddg7_","Value":"1","Quoted":false,"Path":"","Domain":"","Expires":"0001-01-01T00:00:00Z","RawExpires":"","MaxAge":0,"Secure":false,"HttpOnly":false,"SameSite":0,"Partitioned":false,"Raw":"","Unparsed":null}]